turbo_diffusion_ops
turbodiffusion
