Metadata-Version: 2.4
Name: turbodiffusion
Version: 0.1.2
Summary: TurboDiffusion: video generation acceleration framework that could accelerate end-to-end video generation by 100-205x with negligible video quality loss.
Author: Jintao Zhang, Kaiwen Zheng, Kai Jiang, Haoxu Wang
License:                                 Apache License
Project-URL: Homepage, https://github.com/thu-ml/TurboDiffusion
Project-URL: Repository, https://github.com/thu-ml/TurboDiffusion
Classifier: Programming Language :: Python :: 3
Classifier: License :: OSI Approved :: Apache Software License
Requires-Python: >=3.9
License-File: LICENSE
Requires-Dist: torch>=2.7.0
Requires-Dist: triton>=3.3.0
Requires-Dist: flash-attn
Requires-Dist: einops
Requires-Dist: numpy
Requires-Dist: pillow
Requires-Dist: loguru
Requires-Dist: imageio[ffmpeg]
Requires-Dist: pandas
Requires-Dist: PyYAML
Requires-Dist: omegaconf
Requires-Dist: attrs
Requires-Dist: fvcore
Requires-Dist: ftfy
Requires-Dist: regex
Requires-Dist: transformers
Requires-Dist: nvidia-ml-py
Dynamic: license-file
